<?xml version="1.0" encoding="UTF-8"?>
<objects serializationModel="Studio.02.02.00">
	<object class="SandboxScene" id="{d5b504a7-2916-40cf-a8fa-f745d17b9b1c}">
		<property name="name">
			<value>STAD SHOOTER</value>
		</property>
		<relationship name="folder">
			<destination>{035113b3-5093-44f2-b000-18465443bea9}</destination>
		</relationship>
		<relationship name="markerTracks">
			<destination>{e510e46b-8bc8-4ece-99db-810d8203ef01}</destination>
		</relationship>
		<relationship name="timeline">
			<destination>{ba4fbdd4-e95a-43f5-a90f-6b6f7bb7b449}</destination>
		</relationship>
		<relationship name="listeners">
			<destination>{d397bac0-7e8a-432f-bd9c-fc679944ac94}</destination>
		</relationship>
		<relationship name="emitters">
			<destination>{ba7c8e42-4ae9-4906-a0c3-a0523832caf7}</destination>
			<destination>{62b319ef-cbd3-4a75-a838-dc33bc7a82b4}</destination>
			<destination>{551826be-363b-46b7-9f27-f1492208d9a5}</destination>
			<destination>{8d1fa24e-b151-4675-8833-059954183498}</destination>
			<destination>{ee9243b8-b5c3-4ff3-a3bb-1bfdb59cbc94}</destination>
			<destination>{4fc1a1f3-dcd9-4b27-b729-13874170a131}</destination>
			<destination>{354897e4-4655-4ab8-9fb6-6296f357a573}</destination>
			<destination>{9719a751-a77e-4b68-93a4-6aca271f4aa7}</destination>
			<destination>{c0dfc8ea-288d-4215-986f-6d2f1edfaa3d}</destination>
			<destination>{3b817046-c8cc-4352-ab6f-e77fda453ddc}</destination>
			<destination>{6e98c3ca-c5c9-4313-8921-210dc51bb883}</destination>
		</relationship>
	</object>
	<object class="MarkerTrack" id="{e510e46b-8bc8-4ece-99db-810d8203ef01}" />
	<object class="Timeline" id="{ba4fbdd4-e95a-43f5-a90f-6b6f7bb7b449}" />
	<object class="SandboxListener" id="{d397bac0-7e8a-432f-bd9c-fc679944ac94}">
		<property name="positionX">
			<value>0.075000003</value>
		</property>
		<property name="positionZ">
			<value>-0.150000006</value>
		</property>
	</object>
	<object class="SandboxEmitter" id="{ba7c8e42-4ae9-4906-a0c3-a0523832caf7}">
		<property name="positionX">
			<value>-1.99782538</value>
		</property>
		<property name="positionZ">
			<value>-0.131651387</value>
		</property>
		<property name="rotationY">
			<value>-92.1195755</value>
		</property>
		<relationship name="event">
			<destination>{c374ee80-24f4-4917-bb9d-de40e5b391cf}</destination>
		</relationship>
	</object>
	<object class="SandboxEmitter" id="{62b319ef-cbd3-4a75-a838-dc33bc7a82b4}">
		<property name="positionX">
			<value>25.8509007</value>
		</property>
		<property name="positionZ">
			<value>37.822834</value>
		</property>
		<relationship name="event">
			<destination>{be35a58b-8803-4867-904d-50446d13ea22}</destination>
		</relationship>
	</object>
	<object class="SandboxEmitter" id="{551826be-363b-46b7-9f27-f1492208d9a5}">
		<property name="positionX">
			<value>3.06413221</value>
		</property>
		<property name="positionZ">
			<value>29.2925777</value>
		</property>
		<property name="rotationY">
			<value>21.2813301</value>
		</property>
		<relationship name="event">
			<destination>{fc32d666-3dc6-46f7-9540-6bddc03b45b2}</destination>
		</relationship>
	</object>
	<object class="SandboxEmitter" id="{8d1fa24e-b151-4675-8833-059954183498}">
		<property name="positionX">
			<value>-14.8538494</value>
		</property>
		<property name="positionZ">
			<value>44.0214081</value>
		</property>
		<relationship name="event">
			<destination>{d0cb698c-6c16-44c6-bb10-91ea69e6d695}</destination>
		</relationship>
	</object>
	<object class="SandboxEmitter" id="{ee9243b8-b5c3-4ff3-a3bb-1bfdb59cbc94}">
		<property name="positionX">
			<value>-3.64594555</value>
		</property>
		<property name="positionZ">
			<value>3.24462206e-07</value>
		</property>
		<property name="rotationY">
			<value>-118.594162</value>
		</property>
		<relationship name="event">
			<destination>{a967791e-6d06-4d2f-9745-56b23f6f463e}</destination>
		</relationship>
	</object>
	<object class="SandboxEmitter" id="{4fc1a1f3-dcd9-4b27-b729-13874170a131}">
		<property name="positionX">
			<value>3.5109098</value>
		</property>
		<property name="positionZ">
			<value>-0.135034993</value>
		</property>
		<relationship name="event">
			<destination>{3666fc1d-6f44-484a-b8cf-d0f224b32ce6}</destination>
		</relationship>
	</object>
	<object class="SandboxEmitter" id="{354897e4-4655-4ab8-9fb6-6296f357a573}">
		<property name="positionX">
			<value>4.99629498</value>
		</property>
		<property name="positionZ">
			<value>42.1309166</value>
		</property>
		<relationship name="event">
			<destination>{89f58f79-50c3-4f83-83ac-87a787e8a087}</destination>
		</relationship>
	</object>
	<object class="SandboxEmitter" id="{9719a751-a77e-4b68-93a4-6aca271f4aa7}">
		<property name="positionX">
			<value>-2.97076988</value>
		</property>
		<property name="positionZ">
			<value>39.8353233</value>
		</property>
		<relationship name="event">
			<destination>{5ee7b794-bf64-49ef-b658-924adfa8fb69}</destination>
		</relationship>
	</object>
	<object class="SandboxEmitter" id="{c0dfc8ea-288d-4215-986f-6d2f1edfaa3d}">
		<property name="positionX">
			<value>-0.135034993</value>
		</property>
		<property name="positionZ">
			<value>39.9703598</value>
		</property>
		<relationship name="event">
			<destination>{6058189f-9357-4682-9295-a75359ae6084}</destination>
		</relationship>
	</object>
	<object class="SandboxEmitter" id="{3b817046-c8cc-4352-ab6f-e77fda453ddc}">
		<property name="positionX">
			<value>16.2753773</value>
		</property>
		<property name="positionZ">
			<value>21.5043697</value>
		</property>
		<property name="rotationY">
			<value>-166.175705</value>
		</property>
		<relationship name="event">
			<destination>{05a394ef-7d5a-4523-b001-08033c0f9e64}</destination>
		</relationship>
	</object>
	<object class="SandboxEmitter" id="{6e98c3ca-c5c9-4313-8921-210dc51bb883}">
		<property name="positionX">
			<value>6.88678455</value>
		</property>
		<property name="positionZ">
			<value>-0.270069987</value>
		</property>
		<relationship name="sandboxParameters">
			<destination>{05e1f418-f7c1-4950-87d3-335bed5d5ab6}</destination>
		</relationship>
		<relationship name="event">
			<destination>{825a13b8-36f7-4306-817b-d04a66d72c79}</destination>
		</relationship>
	</object>
	<object class="SandboxParameter" id="{05e1f418-f7c1-4950-87d3-335bed5d5ab6}">
		<property name="parameterValue">
			<value>1</value>
		</property>
		<relationship name="parameter">
			<destination>{555a24d1-291d-458d-9967-520adede5963}</destination>
		</relationship>
	</object>
</objects>
